ura_api/__init__.py
ura_api/exception.py
ura_api/ura_api.py
ura_api_chengguan-0.0.1.dist-info/LICENSE
ura_api_chengguan-0.0.1.dist-info/METADATA
ura_api_chengguan-0.0.1.dist-info/WHEEL
ura_api_chengguan-0.0.1.dist-info/top_level.txt
ura_api_chengguan-0.0.1.dist-info/RECORD
