Metadata-Version: 2.1
Name: ura_api-chengguan
Version: 0.0.1
Summary: A python wrapper to URA APIs.
Home-page: https://github.com/chengguan/ura_api
Author: Teo Cheng Guan
Author-email: chengguan.teo@gmail.com
License: UNKNOWN
Project-URL: Bug Tracker, https://github.com/chengguan/ura_api/issues
Platform: UNKNOWN
Classifier: Programming Language :: Python :: 3
Classifier: License :: OSI Approved :: MIT License
Classifier: Operating System :: OS Independent
Requires-Python: >=3.6
License-File: LICENSE
